{
	"configurations" : 
	[
		{
			"directories" : 
			[
				{
					"build" : ".",
					"hasInstallRule" : true,
					"jsonFile" : "directory-.-9f5b3480866800e737e1.json",
					"minimumCMakeVersion" : 
					{
						"string" : "3.12"
					},
					"projectIndex" : 0,
					"source" : ".",
					"targetIndexes" : 
					[
						0,
						1
					]
				}
			],
			"name" : "",
			"projects" : 
			[
				{
					"directoryIndexes" : 
					[
						0
					],
					"name" : "baldybot_description",
					"targetIndexes" : 
					[
						0,
						1
					]
				}
			],
			"targets" : 
			[
				{
					"directoryIndex" : 0,
					"id" : "baldybot_description_uninstall::@6890427a1f51a3e7e1df",
					"jsonFile" : "target-baldybot_description_uninstall-3f8dab662d336c416aea.json",
					"name" : "baldybot_description_uninstall",
					"projectIndex" : 0
				},
				{
					"directoryIndex" : 0,
					"id" : "uninstall::@6890427a1f51a3e7e1df",
					"jsonFile" : "target-uninstall-8a6383a69dc3bc835689.json",
					"name" : "uninstall",
					"projectIndex" : 0
				}
			]
		}
	],
	"kind" : "codemodel",
	"paths" : 
	{
		"build" : "/home/itti_jammy/RoverBaldies_ws/build/baldybot_description",
		"source" : "/home/itti_jammy/RoverBaldies_ws/src/baldybot_description"
	},
	"version" : 
	{
		"major" : 2,
		"minor" : 3
	}
}
